{
  "full_text":{
    "0":"beyonc\u00e9 better be performing",
    "1":"Beyonc\u00e9 ties Grammy record after leading nominations with 9 https:\/\/t.co\/cqceUnbjnC",
    "2":"On Tuesday, Beyonc\u00e9 tied her husband Jay-Z as the artist with the most career Grammy nominations with 88 nods each.",
    "3":"Sitting back and seeing the chaos of people scrambling and crashing Ticketmaster for human white claw Taylor Swift tickets like I\u2019m not gonna do the same thing for Beyonc\u00e9 tickets",
    "4":"But Beyonc\u00e9 do need to stop playing &amp; come up off them videos tho.",
    "5":"There's so much I want to say in here sometimes but Ima just express my joy for Beyonce instead. I hope she wins every damn thing.",
    "6":"Happy of course that Beyonce is bringing some new interest to the category, but a @sofitukker snub is unacceptable",
    "7":"@MessyMyles @Beyonce Petty!!",
    "8":"@KELLYROWLAND @Beyonce @michellewilliams @LeToyaLuckett @destinychild https:\/\/t.co\/WMkBH5p7HE",
    "9":"Would love to see a bunch of celebrities fund their operations.\n\n@ladygaga @taylorswift13 @eltonofficial @Beyonce @TheEllenShow @cyndilauper @ActuallyNPH @DrewBarrymore @GeorgeTakei @kerrywashington https:\/\/t.co\/8Tfcn5hIQa",
    "10":"Waiting for Jay-Z, Beyonce, Diddy, Shaq, and Meek Mill to respond to Ye or they gone call him crazy?",
    "11":"Beyonc\u00e9 Reminded Me That Teaching Is an Art. This Is Why We Must Invest in Teacher Prep Programs.\n\nRead more from @TeachPlusIL Policy Fellowship alumnus Corey Winchester here:\n\nhttps:\/\/t.co\/lNoeEHyDaP",
    "12":"Beyonc\u00e9 emotions always seemed so real on this one \u261d\ud83c\udffe https:\/\/t.co\/saFI9JoefM",
    "13":"@JKs_FlowerGirl @chartdata @taylorswift13 @Harry_Styles @BTS_twt @Beyonce @oliviarodrigo @Adele @fleetwoodmac No that's is not payola at all. Payola is strictly record labels bribing radio stations. Payola has nothing to do with  Spotify at all cause it doesn't qualify as a radio station.  And do you give listeners a free week of Spotify when they can just use the free version of it???",
    "14":"@JKs_FlowerGirl @chartdata @taylorswift13 @Harry_Styles @BTS_twt @Beyonce @oliviarodrigo @Adele @fleetwoodmac I don't think you understand who payola really works my friend",
    "15":"@BuddyNoLove I think people think she\u2019s still in the shadow of Beyonc\u00e9 so she should be a certain way, but they don\u2019t know her, so I don\u2019t get it.",
    "16":"E le fi Janet Jackson wey Beyonc\u00e9 lai lai\n\n- Ba waasi",
    "17":"Beyonce said \u201cyeah you hurt me but I learned a lot along the way\u201d .."
  },
  "date":{
    "0":1668619891000,
    "1":1668568023000,
    "2":1668564998000,
    "3":1668556817000,
    "4":1668551532000,
    "5":1668551482000,
    "6":1668538711000,
    "7":1668535947000,
    "8":1668409162000,
    "9":1668327966000,
    "10":1668260098000,
    "11":1668190500000,
    "12":1668187141000,
    "13":1668097399000,
    "14":1668064646000,
    "15":1668011382000,
    "16":1667997657000,
    "17":1667977974000
  },
  "polarity":{
    "0":0.5,
    "1":0.0,
    "2":0.5,
    "3":0.0,
    "4":0.0,
    "5":0.4333333333,
    "6":0.4681818182,
    "7":0.0,
    "8":0.0,
    "9":0.5,
    "10":-0.6,
    "11":0.5,
    "12":0.2,
    "13":0.4,
    "14":0.2,
    "15":0.2142857143,
    "16":0.0,
    "17":0.0
  },
  "mean_polarity":{
    "0":0.1842111592,
    "1":0.1842111592,
    "2":0.1842111592,
    "3":0.1842111592,
    "4":0.1842111592,
    "5":0.1842111592,
    "6":0.1842111592,
    "7":0.1842111592,
    "8":0.1842111592,
    "9":0.1842111592,
    "10":0.1842111592,
    "11":0.1842111592,
    "12":0.1842111592,
    "13":0.1842111592,
    "14":0.1842111592,
    "15":0.1842111592,
    "16":0.1842111592,
    "17":0.1842111592
  },
  "subjectivity":{
    "0":0.5,
    "1":0.0,
    "2":0.5,
    "3":0.05625,
    "4":0.0,
    "5":0.2,
    "6":0.7272727273,
    "7":0.0,
    "8":0.0,
    "9":0.6,
    "10":0.9,
    "11":0.5,
    "12":0.3,
    "13":0.8,
    "14":0.2,
    "15":0.5714285714,
    "16":0.0,
    "17":0.0
  },
  "mean_subjectivity":{
    "0":0.3252750722,
    "1":0.3252750722,
    "2":0.3252750722,
    "3":0.3252750722,
    "4":0.3252750722,
    "5":0.3252750722,
    "6":0.3252750722,
    "7":0.3252750722,
    "8":0.3252750722,
    "9":0.3252750722,
    "10":0.3252750722,
    "11":0.3252750722,
    "12":0.3252750722,
    "13":0.3252750722,
    "14":0.3252750722,
    "15":0.3252750722,
    "16":0.3252750722,
    "17":0.3252750722
  },
  "screen_name":{
    "0":"JoyBerriee",
    "1":"ArkansasOnline",
    "2":"HCE1985",
    "3":"AlexisCalhoun",
    "4":"kayshaco",
    "5":"LaToyatheeAlien",
    "6":"AJisTweeting",
    "7":"mzdoubleg",
    "8":"ShawnRoland5",
    "9":"DHStom",
    "10":"WonnJamesss",
    "11":"teachplusar",
    "12":"TheAvidAquarian",
    "13":"Afternoonhewn",
    "14":"Afternoonhewn",
    "15":"LouManoti",
    "16":"theSmoothbabs",
    "17":"realtreyxduece"
  },
  "Likes":{
    "0":0,
    "1":0,
    "2":0,
    "3":1,
    "4":0,
    "5":0,
    "6":0,
    "7":0,
    "8":1,
    "9":1,
    "10":0,
    "11":0,
    "12":1,
    "13":0,
    "14":0,
    "15":0,
    "16":0,
    "17":1
  },
  "RTs":{
    "0":0,
    "1":0,
    "2":0,
    "3":2,
    "4":0,
    "5":0,
    "6":0,
    "7":0,
    "8":0,
    "9":0,
    "10":0,
    "11":0,
    "12":0,
    "13":0,
    "14":0,
    "15":0,
    "16":0,
    "17":1
  },
  "state":{
    "0":"Arkansas",
    "1":"Arkansas",
    "2":"Arkansas",
    "3":"Arkansas",
    "4":"Arkansas",
    "5":"Arkansas",
    "6":"Arkansas",
    "7":"Arkansas",
    "8":"Arkansas",
    "9":"Arkansas",
    "10":"Arkansas",
    "11":"Arkansas",
    "12":"Arkansas",
    "13":"Arkansas",
    "14":"Arkansas",
    "15":"Arkansas",
    "16":"Arkansas",
    "17":"Arkansas"
  }
}