{
  "full_text":{
    "0":"@Number10cat Amazing how everyone forgets that Stalin also invaded Poland on the same day Adolf did.",
    "1":"@julia_jusa1 Einfach die aktuelle Pressekonferenz nach den 7. Rammsteintreffen ansehen, Milley erkl\u00e4rt ganz klar, dass die Ukraine gewinnen wird. Und die Entscheidung sich nach Stalin und Hitler nicht dem n\u00e4chsten Massenm\u00f6rder auszuliefern hat die Ukraine getroffen.",
    "2":"@_juliaschramm Quelle f\u00fcr so einen linksfaschistischen Bullshit! Stalin w\u00fcrde dir die F\u00fc\u00dfe k\u00fcssen!",
    "3":"@MauriceHoefgen Sagt ein Linksfaschist, der am liebsten die Leistungsgesellschaft f\u00fcr ihre Arbeit mit noch mehr Steuern bestrafen und die Arbeitsunwilligen belohnen w\u00fcrde! Purer ekelhafter Kommunismus! Stalin w\u00e4re auf dich du Bettpupser!\ud83e\udd22\ud83e\udd2e",
    "4":"@Zanderilmagno Very very underrated war, Stalin bottled it again too",
    "5":"@AstralPreobraz1 @BotakozKassymb1 But not in the time of mass murders under Stalin. We were talking about the Soviet Union, not about today.",
    "6":"@CdnComrade Stalin loves you, Comrade! https:\/\/t.co\/fWDUa8wQ6Z",
    "7":"Stalin war links\nHitler war rechts",
    "8":"@4lki2 K\u00f6nnen wir uns darauf einigen das sowohl Hilter als auch Stalin keine georgisten waren die das Land besteuern und dies das eigentliche Problem ist ? \n\nWobei Stalin nahm meine ich den Bauern das Land weg was ja auch eine Form von \"\u00f6ffentlichen\" Land ist...",
    "9":"@KUHoopes @LaArqueologa @TonyAngelo Of course not, but look, if you found out, that Trotsky believed in Atlantis (for himself), but Lenin and Stalin did not, does this mean that \"the Communists\" believed in Atlantis?",
    "10":"@Plastik_Brewin @Aufdecker Mattias Desmet erkl\u00e4rt den Unterschied in dem Video: wie z.B. unter Stalin geh\u00f6rt eine Pseudowissenschaft dazu, damit Menschen folgen. In einer Diktatur ist es die Macht des Diktators, der z.B. bestrafen kann.\nhttps:\/\/t.co\/GSL6dQetx1",
    "11":"@craigthomler @KyivIndependent It was predominantly inhabited by Tatars for around 600 years until the Russians ethnically cleansed them from 19. century onwards. Stalin forcefully displaced last few in 1944. When Krushchev gifted Crimea to Ukraine in 1954, it was 75% Russian. In 2014, Ukr\u2019s were around 16%.",
    "12":"@UlrichAlois1 @schmidja2017 @Bundeskanzler Soll das eine Neuauflage der Hitler \/ Stalin Verbindung werden?",
    "13":"@DrMaikGoette @rugga76 @usagi67 @peter_simone dass das so ist, sieht man auch daran, dass man H problemlos durch Mao oder Stalin ersetzen k\u00f6nnte, ohne dass viele Ansto\u00df  nehmen w\u00fcrden.",
    "14":"@ScepticBookworm @EchteFreiheit @RainerVenino @FalkTG Man sieht auch in Deutschland, dass diese Katastrophenkommunikation (\"W\u00e4hlt mich, denn Partei X ist die Reinkarnation von Stalin\/Hitler\") f\u00fcr viele kein akzeptables Angebot mehr ist.",
    "15":"@dieser_Schuft Du hast dabei auch die Gr\u00fcnen und Sozen vergessen! Linksfaschismus ist uncool - keiner will Stalin!",
    "16":"@russophileLs I think that he forgot to put Donald Trump in the list of \"Good People\", alongside Putin, Xi, Stalin, Mao, Orban etc....\nBut Hitler was never a \"Liberal Insanity\", instead he was a fascist insanity, alongside with the \"Good People\" mentioned earlier...",
    "17":"@StradaVictor Que se puede esperar de alguien que admira a Stalin? #ElINENoSeToca #ElINESeQueda",
    "18":"@FridayForFuture Tut ihr das nicht auch? Jeder der anders denkt wird mundtot gemacht! Tr\u00e4umt ihr nicht auch von der Umverteilung und einer \u00d6kodiktatur! Pol Pot, Stalin, Honecker, Mao, Castro, Ch Guevera, Ch\u00e1vez, Ho CHI Min, die RAF waren auch nicht gerade Grant f\u00fcr Meinungsfreiheit wert it!! https:\/\/t.co\/wLzfbbqpCI",
    "19":"@wildirishrosie Starmer is a dangerous authoritarian monster. If he ever sees power there will be a bonfire of UK civil liberties. It would be like  handing power to Joseph Stalin.",
    "20":"@Prabha_jii @PMOIndia @mkstalin @GovernorTN @tnpoliceoffl shocked &amp; shamed to see two ministers of TN Govt watching a uniformed policeman die on the road &amp; others watching !As a Senior War Veteran,my sympathies. Mr.Stalin,a dynamic CM, Please sack the ministers &amp; help his family. https:\/\/t.co\/OWx1bvR9Qz"
  },
  "date":{
    "0":1668701163000,
    "1":1668671234000,
    "2":1668556562000,
    "3":1668555051000,
    "4":1668543714000,
    "5":1668541846000,
    "6":1668446825000,
    "7":1668423100000,
    "8":1668421239000,
    "9":1668375878000,
    "10":1668345382000,
    "11":1668343889000,
    "12":1668258256000,
    "13":1668150168000,
    "14":1668068807000,
    "15":1668036405000,
    "16":1668006324000,
    "17":1667996267000,
    "18":1667984837000,
    "19":1667974150000,
    "20":1667968014000
  },
  "polarity":{
    "0":0.3,
    "1":0.0,
    "2":0.0,
    "3":0.0,
    "4":0.26,
    "5":0.0,
    "6":0.0,
    "7":0.0,
    "8":0.0,
    "9":-0.3125,
    "10":0.0,
    "11":0.075,
    "12":0.0,
    "13":0.0,
    "14":0.0,
    "15":0.0,
    "16":0.4666666667,
    "17":0.0,
    "18":0.0,
    "19":-0.6,
    "20":-0.4375
  },
  "mean_polarity":{
    "0":-0.0118253968,
    "1":-0.0118253968,
    "2":-0.0118253968,
    "3":-0.0118253968,
    "4":-0.0118253968,
    "5":-0.0118253968,
    "6":-0.0118253968,
    "7":-0.0118253968,
    "8":-0.0118253968,
    "9":-0.0118253968,
    "10":-0.0118253968,
    "11":-0.0118253968,
    "12":-0.0118253968,
    "13":-0.0118253968,
    "14":-0.0118253968,
    "15":-0.0118253968,
    "16":-0.0118253968,
    "17":-0.0118253968,
    "18":-0.0118253968,
    "19":-0.0118253968,
    "20":-0.0118253968
  },
  "subjectivity":{
    "0":0.5125,
    "1":0.0,
    "2":0.0,
    "3":0.0,
    "4":0.39,
    "5":0.0,
    "6":0.0,
    "7":0.0,
    "8":0.0,
    "9":0.6875,
    "10":0.0,
    "11":0.2916666667,
    "12":0.0,
    "13":0.0,
    "14":0.0,
    "15":0.0,
    "16":0.5666666667,
    "17":0.0,
    "18":0.0,
    "19":0.9,
    "20":0.4833333333
  },
  "mean_subjectivity":{
    "0":0.1824603175,
    "1":0.1824603175,
    "2":0.1824603175,
    "3":0.1824603175,
    "4":0.1824603175,
    "5":0.1824603175,
    "6":0.1824603175,
    "7":0.1824603175,
    "8":0.1824603175,
    "9":0.1824603175,
    "10":0.1824603175,
    "11":0.1824603175,
    "12":0.1824603175,
    "13":0.1824603175,
    "14":0.1824603175,
    "15":0.1824603175,
    "16":0.1824603175,
    "17":0.1824603175,
    "18":0.1824603175,
    "19":0.1824603175,
    "20":0.1824603175
  },
  "screen_name":{
    "0":"MotorsportMark",
    "1":"ClausAbleiter",
    "2":"Sebasti75414497",
    "3":"Sebasti75414497",
    "4":"Napoleonismo",
    "5":"ClausAbleiter",
    "6":"WowbaggerUEV",
    "7":"MariusIllmann",
    "8":"MariusIllmann",
    "9":"Atlantis_Scout",
    "10":"ulrike_faassen",
    "11":"OzzyFra",
    "12":"hmger_hoerby",
    "13":"ProfRieck",
    "14":"db11fs",
    "15":"Sebasti75414497",
    "16":"sobu_hasy",
    "17":"LibreSabina",
    "18":"frank5403",
    "19":"KerryBurgess",
    "20":"Colonelgopi"
  },
  "Likes":{
    "0":0,
    "1":10,
    "2":0,
    "3":3,
    "4":1,
    "5":0,
    "6":0,
    "7":7,
    "8":2,
    "9":0,
    "10":1,
    "11":0,
    "12":1,
    "13":0,
    "14":13,
    "15":0,
    "16":0,
    "17":0,
    "18":0,
    "19":24,
    "20":0
  },
  "RTs":{
    "0":0,
    "1":0,
    "2":0,
    "3":0,
    "4":0,
    "5":0,
    "6":0,
    "7":0,
    "8":0,
    "9":0,
    "10":0,
    "11":0,
    "12":0,
    "13":0,
    "14":0,
    "15":0,
    "16":0,
    "17":0,
    "18":0,
    "19":0,
    "20":1
  },
  "state":{
    "0":"Kentucky",
    "1":"Kentucky",
    "2":"Kentucky",
    "3":"Kentucky",
    "4":"Kentucky",
    "5":"Kentucky",
    "6":"Kentucky",
    "7":"Kentucky",
    "8":"Kentucky",
    "9":"Kentucky",
    "10":"Kentucky",
    "11":"Kentucky",
    "12":"Kentucky",
    "13":"Kentucky",
    "14":"Kentucky",
    "15":"Kentucky",
    "16":"Kentucky",
    "17":"Kentucky",
    "18":"Kentucky",
    "19":"Kentucky",
    "20":"Kentucky"
  }
}