{
  "full_text":{
    "0":"leaving this app. thank you for the comedy and news. fuck el*n m*sk \u00af\\_(\u30c4)_\/\u00af.",
    "1":"Fuck That Guy, though.",
    "2":"@YankeesPR @BryanHoch Dude what the fuck",
    "3":"@catturd2 Um...I took the J&amp;J as per my Employers Policy. But I did the One and Done. I now have Retinal Damage in my Right Eye. 3 tiny blind spots due to Retinal Inflammation. I'd like to thank Trump for Operation Warp Speed and Biden for Accelerating it. Fuck Both Parties.",
    "4":"@YourBuddyRichie @elonmusk @nichegamer Imagine the money you've saved. Also, guys like you throw amazing Pizza Parties randomly for your employees. I don't work for you, but damned if I wouldn't be proud to. I hate working for fuck-tard bosses that waste money.",
    "5":"@elite4vivian FUCK YEAH MALE COMBEE",
    "6":"@mr_gh0stly I'm starting to think these triangles were built with cardboard molds, and are just hollow as fuck.",
    "7":"Fuck it, we ball https:\/\/t.co\/Dr8BcSPQLd",
    "8":"@NJBroncoguy84 Holy fuck \ud83d\ude33.",
    "9":"@DeadDogLake Sober up fuck",
    "10":"@Stop_Hammerzeit \u201cFuck the Raider\u201d is the best chant.",
    "11":"WHAT THE FUCK",
    "12":"@HumanKevinJones \ud83d\ude02 I\u2019m fat as fuck, but I lost 50lb and feel like an expert",
    "13":"@TheCheeseball81 The fuck kinda person does that?",
    "14":"Does this mean Izzy is legit scared? He\u2019s always doing some fuck shit",
    "15":"Fuck it, it\u2019ll workout somehow",
    "16":"#UFC281\nI hope Isi gets knocked the fuck out!",
    "17":"Who the fuck, block me report me. Who the fuck is that sick to think this into law? Seriously? Who.  Someone please tell me.  Who. https:\/\/t.co\/wXDhl6UwkK",
    "18":"\u201cfuck it, fuck it! we ball!\u201d",
    "19":"It just feels good in the moment, so you\u2019re just like\u2026fuck it let\u2019s go.",
    "20":"@DailyLoud Who gives a fuck? Not me, just another nigga dead but just richer",
    "21":"One of the best series finales I\u2019ve ever seen. Fuck, I love this show. https:\/\/t.co\/awjzSHbrWE",
    "22":"You know what, go fuck yourself, i dont need you.",
    "23":"The real villain in the Nancy\/Bartise relationship is Nancy\u2019s mom and brother. It ain\u2019t about you two. Fuck right off. #LoveIsBlind",
    "24":"@trappist_e @dysinger @Essing72 @KATUNews Break down the 2nd Amendment: A well regulated militia being necessary to the security of a free state - {Militia\/Military is a necessary evil}, the right of the people to keep and bear arms, {People can have weapons} shall not be infringed{fuck off penpushers}",
    "25":"I\u2019ve had two horrible nightmares last night,  not that it scared me or anything but the fact is it was about the same person twice is weird as fuck.",
    "26":"@AlmghtyBrshSwgg My favorite Pok\u00e9mon is fat fuck",
    "27":"@TheScottCharles @Bolshoibabushka I told Siri to fuck off once and she scolded me for my language.",
    "28":"@gisellnextdoor Woke up hungry as fuck",
    "29":"Once again fuck it.",
    "30":"@RubiRose @RubiRose fuck all that like I\u2019m trynna be with you like ur super bad badder than a toddler in a grocery store chrisean who?? \ud83d\ude02"
  },
  "date":{
    "0":1668655725000,
    "1":1668565715000,
    "2":1668540802000,
    "3":1668505752000,
    "4":1668496068000,
    "5":1668481785000,
    "6":1668471982000,
    "7":1668468659000,
    "8":1668451714000,
    "9":1668451488000,
    "10":1668386205000,
    "11":1668374005000,
    "12":1668360579000,
    "13":1668323861000,
    "14":1668317125000,
    "15":1668315816000,
    "16":1668314436000,
    "17":1668301299000,
    "18":1668300056000,
    "19":1668299933000,
    "20":1668244300000,
    "21":1668225144000,
    "22":1668224677000,
    "23":1668218497000,
    "24":1668217785000,
    "25":1668177292000,
    "26":1668147787000,
    "27":1668096448000,
    "28":1668063529000,
    "29":1668034003000,
    "30":1668017505000
  },
  "polarity":{
    "0":-0.4,
    "1":-0.4,
    "2":-0.4,
    "3":-0.1478571429,
    "4":-0.02,
    "5":-0.2,
    "6":-0.1666666667,
    "7":-0.4,
    "8":-0.4,
    "9":-0.15,
    "10":0.3,
    "11":-0.4,
    "12":-0.4,
    "13":-0.4,
    "14":-0.3041666667,
    "15":-0.4,
    "16":-0.5,
    "17":-0.4619047619,
    "18":-0.5125,
    "19":0.7,
    "20":-0.3,
    "21":0.3666666667,
    "22":-0.4,
    "23":0.0285714286,
    "24":-0.0671201814,
    "25":-0.38,
    "26":0.05,
    "27":-0.4,
    "28":-0.4,
    "29":-0.4,
    "30":-0.2555555556
  },
  "mean_polarity":{
    "0":-0.2329204155,
    "1":-0.2329204155,
    "2":-0.2329204155,
    "3":-0.2329204155,
    "4":-0.2329204155,
    "5":-0.2329204155,
    "6":-0.2329204155,
    "7":-0.2329204155,
    "8":-0.2329204155,
    "9":-0.2329204155,
    "10":-0.2329204155,
    "11":-0.2329204155,
    "12":-0.2329204155,
    "13":-0.2329204155,
    "14":-0.2329204155,
    "15":-0.2329204155,
    "16":-0.2329204155,
    "17":-0.2329204155,
    "18":-0.2329204155,
    "19":-0.2329204155,
    "20":-0.2329204155,
    "21":-0.2329204155,
    "22":-0.2329204155,
    "23":-0.2329204155,
    "24":-0.2329204155,
    "25":-0.2329204155,
    "26":-0.2329204155,
    "27":-0.2329204155,
    "28":-0.2329204155,
    "29":-0.2329204155,
    "30":-0.2329204155
  },
  "subjectivity":{
    "0":0.6,
    "1":0.6,
    "2":0.6,
    "3":0.5354761905,
    "4":0.66,
    "5":0.35,
    "6":0.25,
    "7":0.6,
    "8":0.6,
    "9":0.4,
    "10":0.45,
    "11":0.6,
    "12":0.6,
    "13":0.6,
    "14":0.6958333333,
    "15":0.6,
    "16":0.6,
    "17":0.680952381,
    "18":0.6,
    "19":0.6,
    "20":0.5,
    "21":0.5,
    "22":0.6,
    "23":0.4785714286,
    "24":0.6606575964,
    "25":0.5583333333,
    "26":0.8,
    "27":0.6,
    "28":0.6,
    "29":0.6,
    "30":0.6444444444
  },
  "mean_subjectivity":{
    "0":0.573040926,
    "1":0.573040926,
    "2":0.573040926,
    "3":0.573040926,
    "4":0.573040926,
    "5":0.573040926,
    "6":0.573040926,
    "7":0.573040926,
    "8":0.573040926,
    "9":0.573040926,
    "10":0.573040926,
    "11":0.573040926,
    "12":0.573040926,
    "13":0.573040926,
    "14":0.573040926,
    "15":0.573040926,
    "16":0.573040926,
    "17":0.573040926,
    "18":0.573040926,
    "19":0.573040926,
    "20":0.573040926,
    "21":0.573040926,
    "22":0.573040926,
    "23":0.573040926,
    "24":0.573040926,
    "25":0.573040926,
    "26":0.573040926,
    "27":0.573040926,
    "28":0.573040926,
    "29":0.573040926,
    "30":0.573040926
  },
  "screen_name":{
    "0":"_pitusberry",
    "1":"phetish",
    "2":"RealBossy_",
    "3":"ND_Trucker2",
    "4":"ND_Trucker2",
    "5":"_HamburgerTime",
    "6":"JoeySkylynx",
    "7":"Josh_Haider",
    "8":"arichheinert",
    "9":"LVFFI3",
    "10":"fishdo69",
    "11":"HotHouseHusband",
    "12":"DraftCats",
    "13":"zanth99",
    "14":"NoahDanielH",
    "15":"yocolten",
    "16":"beaks3",
    "17":"TheNortExpo",
    "18":"macanteazure",
    "19":"natelafountain",
    "20":"DylRedbow",
    "21":"DanDohertyBEK",
    "22":"Plenty__Chief",
    "23":"HotHouseHusband",
    "24":"JoeySkylynx",
    "25":"MrBuffaloBoy97",
    "26":"_HamburgerTime",
    "27":"HougenJ",
    "28":"SirLNDSY",
    "29":"KarlannHarrison",
    "30":"billzisbak"
  },
  "Likes":{
    "0":1,
    "1":2,
    "2":0,
    "3":0,
    "4":0,
    "5":2,
    "6":0,
    "7":2,
    "8":0,
    "9":1,
    "10":0,
    "11":0,
    "12":1,
    "13":1,
    "14":0,
    "15":16,
    "16":1,
    "17":0,
    "18":1,
    "19":3,
    "20":0,
    "21":0,
    "22":2,
    "23":0,
    "24":0,
    "25":0,
    "26":1,
    "27":2,
    "28":0,
    "29":0,
    "30":0
  },
  "RTs":{
    "0":0,
    "1":0,
    "2":0,
    "3":0,
    "4":0,
    "5":0,
    "6":0,
    "7":0,
    "8":0,
    "9":0,
    "10":0,
    "11":0,
    "12":0,
    "13":0,
    "14":0,
    "15":0,
    "16":0,
    "17":0,
    "18":0,
    "19":0,
    "20":0,
    "21":0,
    "22":0,
    "23":0,
    "24":0,
    "25":0,
    "26":0,
    "27":0,
    "28":0,
    "29":0,
    "30":0
  },
  "state":{
    "0":"North Dakota",
    "1":"North Dakota",
    "2":"North Dakota",
    "3":"North Dakota",
    "4":"North Dakota",
    "5":"North Dakota",
    "6":"North Dakota",
    "7":"North Dakota",
    "8":"North Dakota",
    "9":"North Dakota",
    "10":"North Dakota",
    "11":"North Dakota",
    "12":"North Dakota",
    "13":"North Dakota",
    "14":"North Dakota",
    "15":"North Dakota",
    "16":"North Dakota",
    "17":"North Dakota",
    "18":"North Dakota",
    "19":"North Dakota",
    "20":"North Dakota",
    "21":"North Dakota",
    "22":"North Dakota",
    "23":"North Dakota",
    "24":"North Dakota",
    "25":"North Dakota",
    "26":"North Dakota",
    "27":"North Dakota",
    "28":"North Dakota",
    "29":"North Dakota",
    "30":"North Dakota"
  }
}