{
  "full_text":{
    "0":"Opinion | CDC's Updated Opioid Guidelines Are Necessary, but Not Sufficient https:\/\/t.co\/njaEzkvMeC",
    "1":"Helping you get your life back.\nLearn more, get in touch with us at https:\/\/t.co\/zgRhe4MoOl or call 405-467-4399.\n.\n.\n.\n#PainRelief #Medication #Opioid #nonOpioid #neuroleptics #PhysicalTherapy #CBT #PainManagement #Oklahoma #ComprehensivePain #CPMO #stress #stressmanagement https:\/\/t.co\/GJRm0VdfQu",
    "2":"FDA Takes New Steps to Support OTC Naloxone for Opioid Overdose https:\/\/t.co\/iD4CuJXglI",
    "3":"No pain from now, only gain.\nLearn more, get in touch with us at https:\/\/t.co\/zgRhe4MWDT or call  405-467-4399.\n.\n.\n.\n#PainRelief #Medication #Opioid #nonOpioid #neuroleptics #PhysicalTherapy #CBT #PainManagement #Oklahoma #ComprehensivePain #CPMO #stress #stressmanagement https:\/\/t.co\/kQLNS7rFta",
    "4":"@liberalpuppy @Jim_Jordan Energy independence \u2705\nMade other countries pay as agreed 4 first time ever\u2705\nPeace in the Middle East due to Abraham Accords\u2705\nMoved US embassy in Israel to Jerusalem \u2705\nGave more money to HBCU\u2019s in history for the next 10ths\u2705\nPrison reform\u2705\nTackled Opioid Crisis\u2705",
    "5":"@BldExpressions I didn't even think about it from the opioid conversation! Are we jailing the pharma company CEOs as well as the pharmacies? Interesting.",
    "6":"Keep Calm And Take The Pain One Day At A Time.\nhttps:\/\/t.co\/JTP0Y735IN\n\n405-467-4399\n.\n.\n.\n#PainRelief #Medication #Opioid #nonOpioid #neuroleptics #PhysicalTherapy #CBT #PainManagement #Oklahoma #ComprehensivePain #CPMO #stress #stressmanagement https:\/\/t.co\/NXEuKRnaoO",
    "7":"A drug that has been used to help people recover from addictions, specifically opioid and alcohol abuse. \n\nTelephone receiver 405-225-8105\nhttps:\/\/t.co\/ltDqIcGAwH\n\n#MedicalCannabis #MedicalMarijuna #OklahomaCity #California #PuertoRico https:\/\/t.co\/LbtOeQPUX7",
    "8":"Walmart set to pay $3.1 billion in opioid settlement https:\/\/t.co\/IiHkOZagiy",
    "9":"If you want to enjoy the party, you must have to get rid of the pain first.\nhttps:\/\/t.co\/JTP0Y735IN\n\n405-467-4399\n\n#PainRelief #Medication #Opioid #nonOpioid #neuroleptics #PhysicalTherapy #CBT #PainManagement #Oklahoma #ComprehensivePain #CPMO #stress #stressmanagement https:\/\/t.co\/QgRkpLBx08",
    "10":"Walmart latest pharmacy chain to propose opioid settlement https:\/\/t.co\/EuTnkKl519",
    "11":"We treat your pain aggravation, we recuperate you.\nhttps:\/\/t.co\/JTP0Y7kH7n\n\n405-467-4399\n.\n.\n.\n#PainRelief #Medication #Opioid #nonOpioid #neuroleptics #PhysicalTherapy #CBT #PainManagement #Oklahoma #ComprehensivePain #CPMO #stress #stressmanagement #medical #medicalcare https:\/\/t.co\/Gog4hB6XYs",
    "12":"Cannabis For Pain: A Scientist Reveals How Weed Engages Our Natural Opioid System https:\/\/t.co\/0nCyol0FaA",
    "13":"Cannabis for pain: A scientist reveals how weed activates our body's opioid system  https:\/\/t.co\/O5RLm2eCTb",
    "14":"We will gift you a new version of yourself.\nhttps:\/\/t.co\/JTP0Y735IN\n\n405-467-4399\n.\n.\n.\n#PainRelief #Medication #Opioid #nonOpioid #neuroleptics #PhysicalTherapy #CBT #PainManagement #Oklahoma #ComprehensivePain #CPMO #stress #stressmanagement https:\/\/t.co\/P7ZEhWq3qn"
  },
  "date":{
    "0":1668812942000,
    "1":1668789001000,
    "2":1668705429000,
    "3":1668702601000,
    "4":1668654641000,
    "5":1668631725000,
    "6":1668616201000,
    "7":1668615777000,
    "8":1668536596000,
    "9":1668530281000,
    "10":1668517382000,
    "11":1668438001000,
    "12":1668333257000,
    "13":1668255890000,
    "14":1668184200000
  },
  "polarity":{
    "0":0.0,
    "1":0.25,
    "2":0.1363636364,
    "3":0.25,
    "4":0.0833333333,
    "5":0.5,
    "6":0.3,
    "7":0.0,
    "8":0.0,
    "9":0.325,
    "10":0.5,
    "11":0.0,
    "12":0.1,
    "13":0.0,
    "14":0.1363636364
  },
  "mean_polarity":{
    "0":0.1720707071,
    "1":0.1720707071,
    "2":0.1720707071,
    "3":0.1720707071,
    "4":0.1720707071,
    "5":0.1720707071,
    "6":0.1720707071,
    "7":0.1720707071,
    "8":0.1720707071,
    "9":0.1720707071,
    "10":0.1720707071,
    "11":0.1720707071,
    "12":0.1720707071,
    "13":0.1720707071,
    "14":0.1720707071
  },
  "subjectivity":{
    "0":1.0,
    "1":0.25,
    "2":0.4545454545,
    "3":0.75,
    "4":0.2638888889,
    "5":0.5,
    "6":0.75,
    "7":0.0,
    "8":0.0,
    "9":0.4166666667,
    "10":0.9,
    "11":0.0,
    "12":0.4,
    "13":0.0,
    "14":0.4545454545
  },
  "mean_subjectivity":{
    "0":0.4093097643,
    "1":0.4093097643,
    "2":0.4093097643,
    "3":0.4093097643,
    "4":0.4093097643,
    "5":0.4093097643,
    "6":0.4093097643,
    "7":0.4093097643,
    "8":0.4093097643,
    "9":0.4093097643,
    "10":0.4093097643,
    "11":0.4093097643,
    "12":0.4093097643,
    "13":0.4093097643,
    "14":0.4093097643
  },
  "screen_name":{
    "0":"KentSmalley",
    "1":"drdeborahnilson",
    "2":"KentSmalley",
    "3":"drdeborahnilson",
    "4":"Bsunsine1974",
    "5":"andredaughty",
    "6":"drdeborahnilson",
    "7":"clendeninmd_",
    "8":"kfor",
    "9":"drdeborahnilson",
    "10":"koconews",
    "11":"drdeborahnilson",
    "12":"elevatedfarmsok",
    "13":"TheCannabisAcc2",
    "14":"drdeborahnilson"
  },
  "Likes":{
    "0":0,
    "1":0,
    "2":0,
    "3":0,
    "4":6,
    "5":1,
    "6":0,
    "7":0,
    "8":2,
    "9":0,
    "10":2,
    "11":0,
    "12":0,
    "13":1,
    "14":0
  },
  "RTs":{
    "0":0,
    "1":0,
    "2":0,
    "3":0,
    "4":0,
    "5":0,
    "6":0,
    "7":0,
    "8":1,
    "9":0,
    "10":1,
    "11":0,
    "12":0,
    "13":0,
    "14":0
  },
  "state":{
    "0":"Oklahoma",
    "1":"Oklahoma",
    "2":"Oklahoma",
    "3":"Oklahoma",
    "4":"Oklahoma",
    "5":"Oklahoma",
    "6":"Oklahoma",
    "7":"Oklahoma",
    "8":"Oklahoma",
    "9":"Oklahoma",
    "10":"Oklahoma",
    "11":"Oklahoma",
    "12":"Oklahoma",
    "13":"Oklahoma",
    "14":"Oklahoma"
  }
}