{
  "full_text":{
    "0":"@elonmusk is a full on idiot and the masses let him get to where he is. I wanna go back to when I didn\u2019t know who the fucker even was.\n\nStan @Snowden",
    "1":"I\u2019m so mad about that fucker taking this incredible tool away from the world but I\u2019m also deeply sad about the connections we\u2019re losing. https:\/\/t.co\/qtOwvNtDEx",
    "2":"@KritHit247 I mute every mother fucker in cod to keep my inner peace LMFAOO",
    "3":"@NUFCRyxn Imagine this fucker on cans of my monster https:\/\/t.co\/kA3bRjc7c2",
    "4":"One of my goals in life is when I walk into a room my presence demands a blow job. I'm not there yet but I'm getting there mother fucker.",
    "5":"@janisonhiatus @Hawaii11022016 @donkoclock @hardboiledblue @BigEers @CaryLloyd63 @MaineChris2TN @MarciaDaughtre1 @Dave9737 @TimGravett @603TD @inspiringnat @Lindsay19851 @notforbot @LowOnIron1 @SilverRaptor3 @RoxineKing @BryanJon7 @SherryChaffin1 @stanspak @MrDyer9 @StephensVina They forgot MTG and Fucker Carlson",
    "6":"THIS. This is how every headline referring to that orange fucker should be handled. https:\/\/t.co\/TDFzi51sq1",
    "7":"Guarantee this is the fucker that's been haunting my nightmares since I was 4. https:\/\/t.co\/b2ZJMbOOe7",
    "8":"The fucker doesn\u2019t have the votes https:\/\/t.co\/N0Hvfw3AOB",
    "9":"can't believe georgie's response to Nikola Orsinov is \"plastic fucker showed up and had to change all my lighbulbs\"",
    "10":"fucker https:\/\/t.co\/FpuZTm0O3O",
    "11":"This fucker is top class but when he\u2019s had a beer and his lass, Peter (@alielrond) get in chat\u2026 unstoppable https:\/\/t.co\/6b1UVY8VqO",
    "12":"If i get to hear Free Bird in game while @unrooolie is chopping people in a chopper... ima die one happy mother fucker https:\/\/t.co\/fDm9ECrWKP",
    "13":"@hansenry Can't show him skating the fucker was too good",
    "14":"Why does this fucker in a cape thing I want to speak to him",
    "15":"Actually scratch that, I'll clone this fucker before I go to bed. I Ain't waiting 21 hours",
    "16":"Can somebody knock this fucker out of the Senate? Come on Iowa, stop electing this piece of shit https:\/\/t.co\/pZkVevns6k",
    "17":"@CarolineBC92 Well that's not great.\ud83e\udd23\ud83e\udd23 Some say it's lucky, but I'd have to disagree. You're coastal but, so this is just one of them things for you.. at least the fucker missed. \ud83e\udd23\ud83e\udd23 Glad all's well with you.\ud83d\udc4d",
    "18":"@SeaOfThieves Just remember if you go team Pendragon, you're going with this goofy fucker, who gets lost in the middle of the sea. https:\/\/t.co\/ANPXeK4eD7",
    "19":"i cant stop thinking about this fucker its driving me insane.",
    "20":"This mother fucker needs to sit his ass on the bench. https:\/\/t.co\/eeYAPMkTDb",
    "21":"And then, and THEN, this fucker started travelling the country and apparently after he killed his kids, decided on a whim to just, you know, take a trip.",
    "22":"The bar tonight had a huge uterus behind the dj and honestly i was so  hype I almost stole that fucker",
    "23":"Big ticket items mother fucker",
    "24":"what a fucker",
    "25":"\ud83e\udea6Shitcoin Casinos\n\u2620\ufe0fYield Scams\n\ud83d\ude35Fiat Institutional Miners\n\nPlebs don\u2019t need no water, let the mother fucker burn \ud83d\udd25\ud83d\udd25\ud83d\udd25\nBURN MOTHERFUCKER BURN https:\/\/t.co\/1ZPwL0VU8t",
    "26":"@Strawhat_Fuzzy AAHHHH YOU FUCKER\u2764\ufe0f\ud83d\udc79",
    "27":"This dumb man who claims to be running my work place tried to throw us under the bus to one another and I called his ass out on it. Blaming me for not taking care of shit he said he would take care of while I was out on my emergency loa. Like mother fucker no.",
    "28":"@RefShinyShoes Read the fine print just make sure that fucker says unlimited miles.",
    "29":"Fucker i keep munching on food after i say i wont...\ud83d\udc41\ud83d\udc44\ud83d\udc41",
    "30":"This fucker should not be as funny as he is https:\/\/t.co\/obPH2mV7e0"
  },
  "date":{
    "0":1668741586000,
    "1":1668736723000,
    "2":1668699905000,
    "3":1668673580000,
    "4":1668660515000,
    "5":1668640650000,
    "6":1668606201000,
    "7":1668527277000,
    "8":1668467485000,
    "9":1668456470000,
    "10":1668449316000,
    "11":1668448358000,
    "12":1668447092000,
    "13":1668439878000,
    "14":1668356420000,
    "15":1668352021000,
    "16":1668351549000,
    "17":1668350504000,
    "18":1668341666000,
    "19":1668321499000,
    "20":1668311259000,
    "21":1668261600000,
    "22":1668237490000,
    "23":1668205790000,
    "24":1668198125000,
    "25":1668174190000,
    "26":1668122977000,
    "27":1668083957000,
    "28":1668079433000,
    "29":1668059113000,
    "30":1668001127000
  },
  "polarity":{
    "0":-0.15,
    "1":-0.075,
    "2":0.0,
    "3":0.0,
    "4":0.0,
    "5":0.0,
    "6":0.0,
    "7":0.0,
    "8":0.0,
    "9":0.0,
    "10":0.0,
    "11":0.5,
    "12":0.2666666667,
    "13":0.7,
    "14":0.0,
    "15":0.0,
    "16":-0.2,
    "17":0.1777777778,
    "18":0.25,
    "19":-1.0,
    "20":0.0,
    "21":-0.075,
    "22":0.2,
    "23":0.0,
    "24":0.0,
    "25":0.0,
    "26":0.0,
    "27":-0.2875,
    "28":0.4583333333,
    "29":0.0,
    "30":0.25
  },
  "mean_polarity":{
    "0":0.0327508961,
    "1":0.0327508961,
    "2":0.0327508961,
    "3":0.0327508961,
    "4":0.0327508961,
    "5":0.0327508961,
    "6":0.0327508961,
    "7":0.0327508961,
    "8":0.0327508961,
    "9":0.0327508961,
    "10":0.0327508961,
    "11":0.0327508961,
    "12":0.0327508961,
    "13":0.0327508961,
    "14":0.0327508961,
    "15":0.0327508961,
    "16":0.0327508961,
    "17":0.0327508961,
    "18":0.0327508961,
    "19":0.0327508961,
    "20":0.0327508961,
    "21":0.0327508961,
    "22":0.0327508961,
    "23":0.0327508961,
    "24":0.0327508961,
    "25":0.0327508961,
    "26":0.0327508961,
    "27":0.0327508961,
    "28":0.0327508961,
    "29":0.0327508961,
    "30":0.0327508961
  },
  "subjectivity":{
    "0":0.45,
    "1":0.9666666667,
    "2":0.1666666667,
    "3":0.0,
    "4":0.0,
    "5":0.0,
    "6":0.0,
    "7":0.0,
    "8":0.0,
    "9":0.0,
    "10":0.0,
    "11":0.5,
    "12":0.7333333333,
    "13":0.6,
    "14":0.0,
    "15":0.1,
    "16":0.8,
    "17":0.7444444444,
    "18":0.5,
    "19":1.0,
    "20":0.0,
    "21":0.175,
    "22":0.8333333333,
    "23":0.1,
    "24":0.0,
    "25":0.0,
    "26":0.0,
    "27":0.65,
    "28":0.6944444444,
    "29":0.0,
    "30":1.0
  },
  "mean_subjectivity":{
    "0":0.3230286738,
    "1":0.3230286738,
    "2":0.3230286738,
    "3":0.3230286738,
    "4":0.3230286738,
    "5":0.3230286738,
    "6":0.3230286738,
    "7":0.3230286738,
    "8":0.3230286738,
    "9":0.3230286738,
    "10":0.3230286738,
    "11":0.3230286738,
    "12":0.3230286738,
    "13":0.3230286738,
    "14":0.3230286738,
    "15":0.3230286738,
    "16":0.3230286738,
    "17":0.3230286738,
    "18":0.3230286738,
    "19":0.3230286738,
    "20":0.3230286738,
    "21":0.3230286738,
    "22":0.3230286738,
    "23":0.3230286738,
    "24":0.3230286738,
    "25":0.3230286738,
    "26":0.3230286738,
    "27":0.3230286738,
    "28":0.3230286738,
    "29":0.3230286738,
    "30":0.3230286738
  },
  "screen_name":{
    "0":"Gsnickerz",
    "1":"katelyn__ann",
    "2":"HexedEmpress",
    "3":"artisan998",
    "4":"Steven_Clark_18",
    "5":"hello_ronda",
    "6":"Von_Hertzog",
    "7":"MaeNicole13",
    "8":"rfpoorlands",
    "9":"darqwing28",
    "10":"Spyrodile",
    "11":"PhattRascal",
    "12":"EvilDylan666",
    "13":"AmishZed",
    "14":"AndrewChristi3",
    "15":"jstahlman13",
    "16":"Matthew70700968",
    "17":"WMcCusker4",
    "18":"Meirno3",
    "19":"ballerina_ari",
    "20":"tomypickett",
    "21":"QuotingEMH",
    "22":"LeicEE_32",
    "23":"JizzOmelette",
    "24":"dudebabii",
    "25":"JonPDiGiacomo",
    "26":"GachaSoba",
    "27":"acidashley7",
    "28":"AHums1985",
    "29":"whereisnatty",
    "30":"Acestarsz"
  },
  "Likes":{
    "0":0,
    "1":1,
    "2":0,
    "3":0,
    "4":0,
    "5":3,
    "6":23,
    "7":2,
    "8":0,
    "9":1,
    "10":81,
    "11":0,
    "12":3,
    "13":2,
    "14":0,
    "15":0,
    "16":0,
    "17":0,
    "18":1,
    "19":3,
    "20":0,
    "21":3,
    "22":1,
    "23":0,
    "24":1,
    "25":4,
    "26":0,
    "27":1,
    "28":1,
    "29":0,
    "30":1
  },
  "RTs":{
    "0":0,
    "1":0,
    "2":0,
    "3":0,
    "4":0,
    "5":1,
    "6":0,
    "7":0,
    "8":0,
    "9":0,
    "10":18,
    "11":0,
    "12":1,
    "13":0,
    "14":0,
    "15":0,
    "16":0,
    "17":0,
    "18":0,
    "19":0,
    "20":0,
    "21":1,
    "22":0,
    "23":0,
    "24":1,
    "25":0,
    "26":0,
    "27":0,
    "28":0,
    "29":0,
    "30":0
  },
  "state":{
    "0":"Pennsylvania",
    "1":"Pennsylvania",
    "2":"Pennsylvania",
    "3":"Pennsylvania",
    "4":"Pennsylvania",
    "5":"Pennsylvania",
    "6":"Pennsylvania",
    "7":"Pennsylvania",
    "8":"Pennsylvania",
    "9":"Pennsylvania",
    "10":"Pennsylvania",
    "11":"Pennsylvania",
    "12":"Pennsylvania",
    "13":"Pennsylvania",
    "14":"Pennsylvania",
    "15":"Pennsylvania",
    "16":"Pennsylvania",
    "17":"Pennsylvania",
    "18":"Pennsylvania",
    "19":"Pennsylvania",
    "20":"Pennsylvania",
    "21":"Pennsylvania",
    "22":"Pennsylvania",
    "23":"Pennsylvania",
    "24":"Pennsylvania",
    "25":"Pennsylvania",
    "26":"Pennsylvania",
    "27":"Pennsylvania",
    "28":"Pennsylvania",
    "29":"Pennsylvania",
    "30":"Pennsylvania"
  }
}