{
  "full_text":{
    "0":"@CFCmerica As long as Weah is there serving Pulisic I am good.",
    "1":"This picture from 2014 #USMNT U17 features #WorldCup2022 players Haji Wright, Christian Pulisic, Luca De La Torre &amp; Tyler Adams. @wugims can you spot an old teammate of yours? Yep, McKinze Gaines. https:\/\/t.co\/JrXY0fuixG",
    "2":"This picture from 2014 #USMNT U17 features #WorldCup2022 players  Haji Wright, Christian Pulisic, Luca De La Torre &amp; Tyler Adams. @wugims can you spot an old teammate of yours? Yep, McKinze Gaines. https:\/\/t.co\/aC1CHBO7uU",
    "3":"Lozano and Pulisic. https:\/\/t.co\/Ungcfj5HrA",
    "4":"@brfootball Better than pulisic.",
    "5":"@GabeBock Look into Chelsea. The top American (Christian Pulisic) plays for this squad so it gives you a rooting interest.",
    "6":"\ud83c\uddfa\ud83c\uddf8 Christian Pulisic in just 9 minutes had completed more successful take-ons (2\/2) than any other player on the pitch fo\u2026",
    "7":"@FOXSports Pulisic is hardly an \"international superstar\"",
    "8":"@suds777 @CFCNiko Bro... I'm not doing this with you \ud83e\udd23\ud83d\ude02 Silva is my guy....I just know the hate against Pulisic is ridiculous.  \ud83e\udd37\ud83c\udffb\u200d\u2640\ufe0f",
    "9":"@cpulisic_10 @ChelseaFCinUSA @usmnt please leave Pulisic out of this game!",
    "10":"@GiantsSBchamps Premier League vs MLS unfortunately (other than Pulisic) I don\u2019t see us beating that",
    "11":"#usmnt XI I\u2019d really like to see take on Wales but won\u2019t: \nTurner\nDest\nCCV\nZimmerman\nJedi\nMusah\nAdams\nLDLT\nPulisic\nSargent\nReyna",
    "12":"And he bearly plays for them too , the World Cup ain\u2019t ready. #USMNT #Pulisic https:\/\/t.co\/H53XmvTaR3",
    "13":"Nothing against haji wright but how you make the World Cup over Pepi and pefok and you have only played 2\/3 games makes zero sense , has to be the pulisic friendship #USMNT",
    "14":"@VivianGonzalez8 Imag\u00ednate a Tuchel le dieron pretemporada y le dieron los fichajes que el quiso y el equipo jugaba a una mierda , Potter que no hizo ni un pedido y no tuvo pretemporada lo quieren echar , lo que uno tiene que leer por Dios y eso que Tuchel fue el que no quiso vender a Pulisic",
    "15":"@CFCargento Yo tambi\u00e9n yo voy con Tuchel pero tambi\u00e9n tiene que hacer una limpieza y mandar a la M a Pulisic a Ziyech y mandar a la banca a Sterling y a Havertz",
    "16":"@AljoGutierrez @Vickroder Hoy la delantera volvi\u00f3 a decepcionar es una l\u00e1grima ver a Sterling de delantero Havertz jugando a nada y Pulisic es una mierda de jugador que no merece estar en el Chelsea.",
    "17":"@realrikilopez Nivel de juego havertz es pobre el segundo gol del City es por culpa de pulisic y ya andan escribiendo Potter Out no mamen Klopp tardo 5 a\u00f1os en ganar una premier y 4 en ganar una champions y estos pendejos andan con sus mamadas hinchas de cristal \ud83d\ude21\ud83d\ude21",
    "18":"Pulisic getting pocketed by a 17 year old \ud83d\ude2d",
    "19":"@CFCUruguay Pulisic se tiene que ir del Chelsea el otro a\u00f1o por favor que mierda de jugador. En serio",
    "20":"@ChelseaFC Come on Chelsea \ud83d\udc99\ud83d\udc99\ud83d\udc99\nAnd Pulisic \ud83c\uddfa\ud83c\uddf2\ud83c\uddfa\ud83c\uddf2\ud83c\uddfa\ud83c\uddf2\ud83c\uddfa\ud83c\uddf2",
    "21":"@CfcSheikh @ChelseaFC @ParimatchGlobal And Pulisic. Let's hope they don't law off the throttle to avoid injury just days before \ud83c\udfc6",
    "22":"@pumalondonboy @Vickroder @FabrizioRomano Yo prefiero vender a Pulisic que a havertz."
  },
  "date":{
    "0":1668664302000,
    "1":1668624860000,
    "2":1668624839000,
    "3":1668570038000,
    "4":1668538787000,
    "5":1668532004000,
    "6":1668483926000,
    "7":1668310006000,
    "8":1668279797000,
    "9":1668276470000,
    "10":1668179024000,
    "11":1668128040000,
    "12":1668111966000,
    "13":1668090686000,
    "14":1668035888000,
    "15":1668032216000,
    "16":1668031686000,
    "17":1668031343000,
    "18":1668030201000,
    "19":1668029160000,
    "20":1668021169000,
    "21":1668020734000,
    "22":1667929751000
  },
  "polarity":{
    "0":0.325,
    "1":0.05,
    "2":0.05,
    "3":0.0,
    "4":0.5,
    "5":0.1666666667,
    "6":0.28125,
    "7":0.0,
    "8":-0.5666666667,
    "9":-0.5,
    "10":-0.125,
    "11":0.2,
    "12":0.2,
    "13":0.0,
    "14":0.0,
    "15":0.0,
    "16":0.0,
    "17":0.0,
    "18":0.1,
    "19":0.0,
    "20":0.0,
    "21":0.0,
    "22":0.0
  },
  "mean_polarity":{
    "0":0.0296195652,
    "1":0.0296195652,
    "2":0.0296195652,
    "3":0.0296195652,
    "4":0.0296195652,
    "5":0.0296195652,
    "6":0.0296195652,
    "7":0.0296195652,
    "8":0.0296195652,
    "9":0.0296195652,
    "10":0.0296195652,
    "11":0.0296195652,
    "12":0.0296195652,
    "13":0.0296195652,
    "14":0.0296195652,
    "15":0.0296195652,
    "16":0.0296195652,
    "17":0.0296195652,
    "18":0.0296195652,
    "19":0.0296195652,
    "20":0.0296195652,
    "21":0.0296195652,
    "22":0.0296195652
  },
  "subjectivity":{
    "0":0.5,
    "1":0.1,
    "2":0.1,
    "3":0.0,
    "4":0.5,
    "5":0.1666666667,
    "6":0.45625,
    "7":0.0,
    "8":0.95,
    "9":0.4,
    "10":0.375,
    "11":0.2,
    "12":0.5,
    "13":1.0,
    "14":0.0,
    "15":0.0,
    "16":0.0,
    "17":0.0,
    "18":0.2,
    "19":0.0,
    "20":0.0,
    "21":0.0,
    "22":0.0
  },
  "mean_subjectivity":{
    "0":0.236865942,
    "1":0.236865942,
    "2":0.236865942,
    "3":0.236865942,
    "4":0.236865942,
    "5":0.236865942,
    "6":0.236865942,
    "7":0.236865942,
    "8":0.236865942,
    "9":0.236865942,
    "10":0.236865942,
    "11":0.236865942,
    "12":0.236865942,
    "13":0.236865942,
    "14":0.236865942,
    "15":0.236865942,
    "16":0.236865942,
    "17":0.236865942,
    "18":0.236865942,
    "19":0.236865942,
    "20":0.236865942,
    "21":0.236865942,
    "22":0.236865942
  },
  "screen_name":{
    "0":"DaDakota",
    "1":"QuBiscuit",
    "2":"QuBiscuit",
    "3":"CVUSMO",
    "4":"njleos3",
    "5":"ptrickmac",
    "6":"NickKitty8",
    "7":"MichaelDavidLC",
    "8":"Kacy222",
    "9":"creggles",
    "10":"AstrosBlast22",
    "11":"WhyThisHat",
    "12":"Brianc51295",
    "13":"Brianc51295",
    "14":"varelamaycol0",
    "15":"varelamaycol0",
    "16":"varelamaycol0",
    "17":"varelamaycol0",
    "18":"MaxCityFC",
    "19":"varelamaycol0",
    "20":"drewaton",
    "21":"drewaton",
    "22":"varelamaycol0"
  },
  "Likes":{
    "0":0,
    "1":1,
    "2":0,
    "3":0,
    "4":1,
    "5":1,
    "6":0,
    "7":0,
    "8":0,
    "9":0,
    "10":1,
    "11":0,
    "12":0,
    "13":0,
    "14":0,
    "15":0,
    "16":3,
    "17":1,
    "18":0,
    "19":0,
    "20":0,
    "21":10,
    "22":1
  },
  "RTs":{
    "0":0,
    "1":0,
    "2":0,
    "3":0,
    "4":0,
    "5":0,
    "6":0,
    "7":0,
    "8":0,
    "9":0,
    "10":0,
    "11":0,
    "12":1,
    "13":0,
    "14":0,
    "15":0,
    "16":0,
    "17":0,
    "18":0,
    "19":0,
    "20":0,
    "21":1,
    "22":0
  },
  "state":{
    "0":"Texas",
    "1":"Texas",
    "2":"Texas",
    "3":"Texas",
    "4":"Texas",
    "5":"Texas",
    "6":"Texas",
    "7":"Texas",
    "8":"Texas",
    "9":"Texas",
    "10":"Texas",
    "11":"Texas",
    "12":"Texas",
    "13":"Texas",
    "14":"Texas",
    "15":"Texas",
    "16":"Texas",
    "17":"Texas",
    "18":"Texas",
    "19":"Texas",
    "20":"Texas",
    "21":"Texas",
    "22":"Texas"
  }
}